Main.py
Trackr.py
umtrackr-1.0.0.dist-info/METADATA
umtrackr-1.0.0.dist-info/WHEEL
umtrackr-1.0.0.dist-info/licenses/LICENSE.txt
umtrackr-1.0.0.dist-info/RECORD
