Metadata-Version: 2.1
Name: UMTrackr
Version: 1.0.0
Summary: A platform for makers, hobbyists, students, and professionals to easily store and visualize data recorded from internet-connected devices
Project-URL: Homepage, https://github.com/University-of-Manitoba-Computer-Science/trackr
Author-email: University of Manitoba Industrial Project <csindustrialproject@umanitoba.ca>
License-File: LICENSE.txt
Classifier: License :: OSI Approved :: MIT License
Classifier: Operating System :: OS Independent
Classifier: Programming Language :: Python :: 3
Requires-Python: >=3.7
